{
    "id": 162560,
    "title": "Lov om ændring af sundhedsloven\\n(Udsendelse af påmindelser med henblik på at forbedre tilslutningen til børnevaccinationsprogrammet m.v.)",
    "documentTypeId": "20",
    "isSagsforlobPeriodValid": true,
    "shortName": "LOV nr 344 af 07/04/2014",
    "documentHtml": "<div class=\"bjelke\">Den fulde tekst</div><p class=\"Titel2\">Lov om ændring af sundhedsloven</p>\r\n<p class=\"UnderTitel2\">(Udsendelse af påmindelser med henblik på at forbedre tilslutningen til børnevaccinationsprogrammet m.v.)</p>\r\n<p class=\"Hymne2\">VI MARGRETHE DEN ANDEN, af Guds Nåde Danmarks Dronning, gør vitterligt:</p>\r\n<p class=\"Hymne2\">Folketinget har vedtaget og Vi ved Vort samtykke stadfæstet følgende lov:</p>\r\n<p class=\"CentreretParagraf\">§ 1</p>\r\n<p class=\"Tekst2\">I sundhedsloven, jf. lovbekendtgørelse nr. 913 af 13. juli 2010, som ændret bl.a. ved § 1 i lov nr. 603 af 18. juni 2012 og senest ved lov nr. 171 af 26. februar 2014, foretages følgende ændringer:</p>\r\n<p class=\"AendringMedNummer\">\r\n   <span class=\"AendringNr\">1.</span> I <span class=\"Italic\">§ 157 a, stk. 6,</span> indsættes efter 1. pkt.:</p>\r\n<p class=\"TekstGenerel\">»Statens Serum Institut har desuden adgang til oplysninger i registeret med henblik på at udsende påmindelser ved manglende vaccination med vacciner, der indgår i det danske børnevaccinationsprogram, eller som tilbydes et barn ved individuelt behov.«</p>\r\n<p class=\"AendringMedNummer\">\r\n   <span class=\"AendringNr\">2.</span> I <span class=\"Italic\">§ 157 a</span> indsættes efter stk. 9 som nyt stykke:</p>\r\n<p class=\"Stk2\">\r\n   <span class=\"StkNr\">»Stk. 10.</span> Ministeren for sundhed og forebyggelse fastsætter nærmere regler om Statens Serum Instituts adgang efter stk. 6 til oplysninger i registeret med henblik på at udsende påmindelser ved manglende vaccination med vacciner, der indgår i det danske børnevaccinationsprogram, eller som tilbydes et barn ved individuelt behov. Ministeren fastsætter desuden regler om Statens Serum Instituts udsendelse af påmindelser.«</p>\r\n<p class=\"TekstGenerel\">Stk. 10 bliver herefter stk. 11.</p>\r\n<p class=\"CentreretParagraf\">§ 2</p>\r\n<p class=\"Stk2\">\r\n   <span class=\"StkNr\">\r\n   </span> Loven træder i kraft den 1. maj 2014.</p><div class=\"Givet\" id=\"Givet\"><p class=\"Givet\" align=\"center\">Givet på Christiansborg Slot, den 7. april 2014</p><p class=\"Segl\" align=\"center\">Under Vor Kongelige Hånd og Segl</p><p class=\"Sign1\" align=\"center\">MARGRETHE R.</p><p class=\"Sign2\" align=\"right\">/ Nick Hækkerup</p></div>",
    "isHistorical": true,
    "editorialNotes": [],
    "alternativeMedia": [],
    "ressort": "Indenrigs- og Sundhedsministeriet",
    "isReprint": false,
    "geografiskDaekningId": 0,
    "retsinfoKlassifikationId": 10,
    "caseHistoryReferenceGroup": [
        {
            "heading": "Sagsforløb 2013/1 LF 101",
            "stateLabel": "Vedtaget",
            "references": [
                {
                    "shortName": "2013/1 SF.L L 101",
                    "title": "Skriftlig fremsættelse (12. december 2013) - L 101",
                    "presentationName": "Skriftlig fremsættelse af lovforslag",
                    "documentTypeId": 380,
                    "documentId": 160705,
                    "eliUri": "/eli/ft/20131XX00284",
                    "externalLink": ""
                },
                {
                    "shortName": "2013/1 LSF 101",
                    "title": "Forslag til Lov om ændring af sundhedsloven\\n(Udsendelse af påmindelser med henblik på at forbedre tilslutningen til børnevaccinationsprogrammet m.v.)",
                    "presentationName": "Lovforslag som fremsat",
                    "documentTypeId": 400,
                    "documentId": 160482,
                    "eliUri": "/eli/ft/201312L00101",
                    "externalLink": ""
                },
                {
                    "shortName": "Udvalgsarbejde",
                    "title": "Udvalgsarbejde",
                    "presentationName": "Udvalgsarbejde",
                    "documentTypeId": -10,
                    "eliUri": "",
                    "externalLink": "http://www.ft.dk/samling/20131/lovforslag/l101/index.htm"
                },
                {
                    "shortName": "2013/1 BTL 101",
                    "title": "Betænkning over Forslag til lov om ændring af sundhedsloven\\n(Udsendelse af påmindelser med henblik på at forbedre tilslutningen til børnevaccinationsprogrammet m.v.)",
                    "presentationName": "Betænkning  over lovforslag",
                    "documentTypeId": 420,
                    "documentId": 162181,
                    "eliUri": "/eli/ft/201314L00560",
                    "externalLink": ""
                },
                {
                    "shortName": "2013/1 LSV 101",
                    "title": "Forslag til Lov om ændring af sundhedsloven\\n(Udsendelse af påmindelser med henblik på at forbedre tilslutningen til børnevaccinationsprogrammet m.v.)",
                    "presentationName": "Lovforslag som vedtaget",
                    "documentTypeId": 410,
                    "documentId": 162490,
                    "eliUri": "/eli/ft/201313L00101",
                    "externalLink": ""
                },
                {
                    "shortName": "LOV nr 344 af 07/04/2014",
                    "title": "Lov om ændring af sundhedsloven\\n(Udsendelse af påmindelser med henblik på at forbedre tilslutningen til børnevaccinationsprogrammet m.v.)",
                    "presentationName": "Ændringslov",
                    "documentTypeId": 20,
                    "documentId": 162560,
                    "eliUri": "/eli/lta/2014/344",
                    "externalLink": ""
                }
            ]
        }
    ],
    "metadata": [
        {
            "displayName": "Offentliggørelsesdato",
            "displayValue": "08/04/2014"
        },
        {
            "displayName": "Accession",
            "displayValue": "A20140034430"
        },
        {
            "displayName": "Entydig dokumentidentifikation",
            "displayValue": "BK001565"
        },
        {
            "displayName": "Dato for førstegangsindlæggelse",
            "displayValue": "08/04/2014"
        },
        {
            "displayName": "Dato for indlæggelse",
            "displayValue": "08/04/2014"
        },
        {
            "displayName": "Dokumenttype",
            "displayValue": "Ændringslov"
        },
        {
            "displayName": "Dokumentets rangering",
            "displayValue": "A "
        },
        {
            "displayName": "Forskriftens nummer",
            "displayValue": "344"
        },
        {
            "displayName": "År for udstedelse",
            "displayValue": "2014"
        },
        {
            "displayName": "Dato for underskrift",
            "displayValue": "07/04/2014"
        },
        {
            "displayName": "Offentliggjort i (publiceringsmedie)",
            "displayValue": "Lovtidende A"
        },
        {
            "displayName": "Ressortministeriets journalnummer",
            "displayValue": "Ministeriet for Sundhed og Forebyggelse, j.nr. 1303116"
        }
    ],
    "pdfLink": {
        "isPdfAvailable": true
    },
    "documentFobTagGroup": [],
    "hasFobTags": false
}