{
    "id": 13754,
    "title": "Cirkulære om ophævelse af cirkulære nr. 64 af 21/5 1984 om beskatning af renter af forsikringsbeløb, der er omfattet af arveafgiftslovens § 5 a)",
    "documentTypeId": "150",
    "isSagsforlobPeriodValid": true,
    "shortName": "CIR nr 83 af 09/06/2000",
    "documentHtml": "<div class=\"bjelke\">Den fulde tekst</div><DIV CLASS=PARA ID=\"INDHOLD\"> \r\n\r\n\r\n\r\n<FONT SIZE=5><P ALIGN=\"CENTER\">Cirkul&aelig;re om oph&aelig;velse af  \r\n\r\n cirkul&aelig;re nr. 64 af 21. maj 1984 om beskatning af renter af  \r\n\r\n forsikringsbel&oslash;b, der er omfattet af arveafgiftslovens §&nbsp;5 a)</P>  \r\n\r\n</FONT>  \r\n\r\n<P>&nbsp;</P>  \r\n\r\n<P ALIGN=\"JUSTIFY\">Cirkul&aelig;re nr. 64 af 21. maj 1984 om beskatning af  \r\n\r\n renter af forsikringsbel&oslash;b, der er omfattet af arveafgiftslovens  \r\n\r\n §&nbsp;5 a), oph&aelig;ves med virkning fra 15<A NAME=\"BM_1_\"></A>. maj  \r\n\r\n 2000.</P>  \r\n\r\n<DIV CLASS=GIVET ID=\"GIVET\">  \r\n\r\n<P CLASS=GIVET ALIGN=\"CENTER\"><I>Skatteministeriet, den 9. juni 2000</I></P>  \r\n\r\n<P CLASS=SIGN1 ALIGN=\"CENTER\">Peter Loft</P>  \r\n\r\n<P CLASS=SIGN2 ALIGN=\"RIGHT\">/Lise Bo Nielsen</P>  \r\n\r\n</DIV><!-- End of \"GIVET\" -->  \r\n\r\n</DIV>",
    "isHistorical": false,
    "editorialNotes": [],
    "alternativeMedia": [],
    "ressort": "Skatteministeriet",
    "isReprint": false,
    "geografiskDaekningId": 0,
    "retsinfoKlassifikationId": 10,
    "caseHistoryReferenceGroup": [],
    "metadata": [
        {
            "displayName": "Offentliggørelsesdato",
            "displayValue": "16/06/2000"
        },
        {
            "displayName": "Accession",
            "displayValue": "C20000008309"
        },
        {
            "displayName": "Entydig dokumentidentifikation",
            "displayValue": "AN000959"
        },
        {
            "displayName": "Dato for førstegangsindlæggelse",
            "displayValue": "16/06/2000"
        },
        {
            "displayName": "Dato for indlæggelse",
            "displayValue": "02/10/2006"
        },
        {
            "displayName": "Dokumenttype",
            "displayValue": "Cirkulære (2 sp)"
        },
        {
            "displayName": "Dokumentets rangering",
            "displayValue": "C "
        },
        {
            "displayName": "Forskriftens nummer",
            "displayValue": "83"
        },
        {
            "displayName": "År for udstedelse",
            "displayValue": "2000"
        },
        {
            "displayName": "Dato for underskrift",
            "displayValue": "09/06/2000"
        },
        {
            "displayName": "Offentliggjort i (publiceringsmedie)",
            "displayValue": "Ministerialtidende"
        },
        {
            "displayName": "Ressortministeriets journalnummer",
            "displayValue": "Skattemin., j.nr. 11.99-512-63"
        }
    ],
    "pdfLink": {
        "isPdfAvailable": false
    },
    "documentFobTagGroup": [],
    "hasFobTags": false
}