{
    "id": 45795,
    "title": "Socialforskningsinstituttets register til brug for Undersøgelsen: Indsatsen over for socialt udstødte. ",
    "documentTypeId": "70",
    "isSagsforlobPeriodValid": false,
    "shortName": "BKR nr 50398 af 17/12/1993",
    "documentHtml": "<div class=\"bjelke\">Den fulde tekst</div><DIV CLASS=PARA ID=\"INDHOLD\"> \r\n\r\n\r\n\r\n<H1 CLASS=TITLE ALIGN=CENTER>Socialforskningsinstituttets register til brug  \r\n\r\n for Undersøgelsen: Indsatsen over for socialt udstødte. </H1>  \r\n\r\n<P></P>  \r\n\r\n<BR>  \r\n\r\n<P>Formålet med registeret er at tilvejebringe oplysninger til en </P>  \r\n\r\n<P>statistisk og videnskabelig belysning af indsatsen over for </P>  \r\n\r\n<P>socialt udstødte, med særligt henblik på at belyse: de sociale </P>  \r\n\r\n<P>boformers, være- og omsorgssteders, samt frivilligt socialt </P>  \r\n\r\n<P>arbejdes betydning. </P>  \r\n\r\n<P>Personkreds: Registeret må kun indeholde oplysninger om brugere </P>  \r\n\r\n<P>af forsorgshjem og herberger og lignende, jf. bistandslovens § </P>  \r\n\r\n<P>105 institutioner i Rinkøbing og Nordjyllands Amter samt </P>  \r\n\r\n<P>Københavns Kommune. </P>  \r\n\r\n<P>Ikrafttrædelsesdato: 17/12/1993. </P>  \r\n\r\n</DIV><div class=\"bjelke\">Officielle noter</div><DIV CLASS=PARA ID=\"NOTER\"> \r\n\r\n\r\n<P>Ingen </P>  \r\n\r\n</DIV>",
    "isHistorical": true,
    "editorialNotes": [
        "Registeransvarlig myndighed: Socialforskningsinstituttet"
    ],
    "alternativeMedia": [],
    "ressort": "Justitsministeriet",
    "isReprint": false,
    "geografiskDaekningId": 0,
    "retsinfoKlassifikationId": 10,
    "caseHistoryReferenceGroup": [],
    "metadata": [
        {
            "displayName": "Offentliggørelsesdato",
            "displayValue": "01/10/1997"
        },
        {
            "displayName": "Accession",
            "displayValue": "G199350398R1"
        },
        {
            "displayName": "Entydig dokumentidentifikation",
            "displayValue": "CM004401"
        },
        {
            "displayName": "Dato for førstegangsindlæggelse",
            "displayValue": "01/10/1997"
        },
        {
            "displayName": "Dato for indlæggelse",
            "displayValue": "06/06/2000"
        },
        {
            "displayName": "Dokumenttype",
            "displayValue": "Registerforskriftsbekendtgørelse"
        },
        {
            "displayName": "Dokumentets rangering",
            "displayValue": "G "
        },
        {
            "displayName": "Forskriftens nummer",
            "displayValue": "50398"
        },
        {
            "displayName": "År for udstedelse",
            "displayValue": "1993"
        },
        {
            "displayName": "Dato for underskrift",
            "displayValue": "17/12/1993"
        },
        {
            "displayName": "Offentliggjort i (publiceringsmedie)",
            "displayValue": "Retsinformation"
        },
        {
            "displayName": "Administrerende myndighed",
            "displayValue": "Registertilsynet"
        },
        {
            "displayName": "Ressortministeriets journalnummer",
            "displayValue": "1993 - 4220 - 0165"
        }
    ],
    "pdfLink": {
        "isPdfAvailable": false
    },
    "documentFobTagGroup": [],
    "hasFobTags": false
}